[{"type":"Feature","geometry":{"type":"Point","coordinates":[-57.63303,-19.028843]},"properties":{}},{"type":"Feature","geometry":{"type":"Point","coordinates":[-57.488861,-19.079306]},"properties":{}},{"type":"Feature","geometry":{"type":"Point","coordinates":[-57.489444,-19.076778]},"properties":{}},{"type":"Feature","geometry":{"type":"Point","coordinates":[-56.761258,-21.333858]},"properties":{}},{"type":"Feature","geometry":{"type":"Point","coordinates":[-57.505725,-19.085621]},"properties":{}},{"type":"Feature","geometry":{"type":"Point","coordinates":[-57.509508,-19.104449]},"properties":{}},{"type":"Feature","geometry":{"type":"Point","coordinates":[-57.575278,-19.263333]},"properties":{}},{"type":"Feature","geometry":{"type":"Point","coordinates":[-57.489444,-19.076778]},"properties":{}},{"type":"Feature","geometry":{"type":"Point","coordinates":[-57.5633333,-17.9011111]},"properties":{}},{"type":"Feature","geometry":{"type":"Point","coordinates":[-57.631526,-19.025759]},"properties":{}},{"type":"Feature","geometry":{"type":"Point","coordinates":[-57.504755,-19.092523]},"properties":{}},{"type":"Feature","geometry":{"type":"Point","coordinates":[-57.633244,-19.028853]},"properties":{}},{"type":"Feature","geometry":{"type":"Point","coordinates":[-57.518914,-19.109013]},"properties":{}},{"type":"Feature","geometry":{"type":"Point","coordinates":[-57.710315,-19.160763]},"properties":{}},{"type":"Feature","geometry":{"type":"Point","coordinates":[-57.624444,-19.020556]},"properties":{}},{"type":"Feature","geometry":{"type":"Point","coordinates":[-57.586944,-19.205278]},"properties":{}},{"type":"Feature","geometry":{"type":"Point","coordinates":[-57.5533333,-17.8605556]},"properties":{}},{"type":"Feature","geometry":{"type":"Point","coordinates":[-57.661944,-19.213333]},"properties":{}},{"type":"Feature","geometry":{"type":"Point","coordinates":[-57.629728,-19.025847]},"properties":{}},{"type":"Feature","geometry":{"type":"Point","coordinates":[-57.488861,-19.079306]},"properties":{}},{"type":"Feature","geometry":{"type":"Point","coordinates":[-56.65375406,-18.42520271]},"properties":{}},{"type":"Feature","geometry":{"type":"Point","coordinates":[-57.629444,-19.018333]},"properties":{}},{"type":"Feature","geometry":{"type":"Point","coordinates":[-54.8908333,-17.6191667]},"properties":{}},{"type":"Feature","geometry":{"type":"Point","coordinates":[-57.857339,-19.234057]},"properties":{}},{"type":"Feature","geometry":{"type":"Point","coordinates":[-57.597785,-19.206124]},"properties":{}},{"type":"Feature","geometry":{"type":"Point","coordinates":[-57.597297,-19.19503]},"properties":{}},{"type":"Feature","geometry":{"type":"Point","coordinates":[-57.500389,-19.236111]},"properties":{}},{"type":"Feature","geometry":{"type":"Point","coordinates":[-57.605637,-19.207026]},"properties":{}},{"type":"Feature","geometry":{"type":"Point","coordinates":[-57.523185,-19.597418]},"properties":{}},{"type":"Feature","geometry":{"type":"Point","coordinates":[-57.440015,-18.929553]},"properties":{}},{"type":"Feature","geometry":{"type":"Point","coordinates":[-57.633333,-19.266667]},"properties":{}},{"type":"Feature","geometry":{"type":"Point","coordinates":[-57.6525,-19.185278]},"properties":{}},{"type":"Feature","geometry":{"type":"Point","coordinates":[-57.835278,-19.229444]},"properties":{}}]