[
  {
    "type": "Feature",
    "geometry": {
      "type": "Point",
      "coordinates": [
        -55.953098297119,
        -10.558099746704
      ]
    },
    "properties": {}
  },
  {
    "type": "Feature",
    "geometry": {
      "type": "Point",
      "coordinates": [
        -66.829787,
        -0.207606
      ]
    },
    "properties": {}
  },
  {
    "type": "Feature",
    "geometry": {
      "type": "Point",
      "coordinates": [
        -67.116657,
        -0.06671
      ]
    },
    "properties": {}
  },
  {
    "type": "Feature",
    "geometry": {
      "type": "Point",
      "coordinates": [
        -67.580929,
        -0.742903
      ]
    },
    "properties": {}
  },
  {
    "type": "Feature",
    "geometry": {
      "type": "Point",
      "coordinates": [
        -66.950509,
        -0.131105
      ]
    },
    "properties": {}
  },
  {
    "type": "Feature",
    "geometry": {
      "type": "Point",
      "coordinates": [
        -66.95,
        -0.13
      ]
    },
    "properties": {}
  },
  {
    "type": "Feature",
    "geometry": {
      "type": "Point",
      "coordinates": [
        -66.966025,
        -0.154754
      ]
    },
    "properties": {}
  },
  {
    "type": "Feature",
    "geometry": {
      "type": "Point",
      "coordinates": [
        -67.43391,
        -0.691586
      ]
    },
    "properties": {}
  },
  {
    "type": "Feature",
    "geometry": {
      "type": "Point",
      "coordinates": [
        -64.91,
        6.91
      ]
    },
    "properties": {}
  },
  {
    "type": "Feature",
    "geometry": {
      "type": "Point",
      "coordinates": [
        -67.023611111111,
        -0.17972222222222
      ]
    },
    "properties": {}
  },
  {
    "type": "Feature",
    "geometry": {
      "type": "Point",
      "coordinates": [
        -66.95,
        -0.12
      ]
    },
    "properties": {}
  },
  {
    "type": "Feature",
    "geometry": {
      "type": "Point",
      "coordinates": [
        -67.887641,
        -0.638415
      ]
    },
    "properties": {}
  },
  {
    "type": "Feature",
    "geometry": {
      "type": "Point",
      "coordinates": [
        -67.00413,
        -0.172528
      ]
    },
    "properties": {}
  },
  {
    "type": "Feature",
    "geometry": {
      "type": "Point",
      "coordinates": [
        -66.92,
        -0.33
      ]
    },
    "properties": {}
  },
  {
    "type": "Feature",
    "geometry": {
      "type": "Point",
      "coordinates": [
        -67.166573,
        -0.083728
      ]
    },
    "properties": {}
  },
  {
    "type": "Feature",
    "geometry": {
      "type": "Point",
      "coordinates": [
        -66.989438,
        1.878895
      ]
    },
    "properties": {}
  },
  {
    "type": "Feature",
    "geometry": {
      "type": "Point",
      "coordinates": [
        -67.095861,
        -0.261795
      ]
    },
    "properties": {}
  },
  {
    "type": "Feature",
    "geometry": {
      "type": "Point",
      "coordinates": [
        -71.937788,
        1.003481
      ]
    },
    "properties": {}
  },
  {
    "type": "Feature",
    "geometry": {
      "type": "Point",
      "coordinates": [
        -67.890833,
        5.331667
      ]
    },
    "properties": {}
  },
  {
    "type": "Feature",
    "geometry": {
      "type": "Point",
      "coordinates": [
        -72.074783,
        0.810821
      ]
    },
    "properties": {}
  },
  {
    "type": "Feature",
    "geometry": {
      "type": "Point",
      "coordinates": [
        -66.844492,
        -0.15575
      ]
    },
    "properties": {}
  },
  {
    "type": "Feature",
    "geometry": {
      "type": "Point",
      "coordinates": [
        -67.085278,
        -0.118056
      ]
    },
    "properties": {}
  },
  {
    "type": "Feature",
    "geometry": {
      "type": "Point",
      "coordinates": [
        -67.03444,
        1.925
      ]
    },
    "properties": {}
  },
  {
    "type": "Feature",
    "geometry": {
      "type": "Point",
      "coordinates": [
        -67.148072,
        -0.030553
      ]
    },
    "properties": {}
  },
  {
    "type": "Feature",
    "geometry": {
      "type": "Point",
      "coordinates": [
        -66.94073,
        -0.146339
      ]
    },
    "properties": {}
  },
  {
    "type": "Feature",
    "geometry": {
      "type": "Point",
      "coordinates": [
        -66.943692,
        1.882912
      ]
    },
    "properties": {}
  },
  {
    "type": "Feature",
    "geometry": {
      "type": "Point",
      "coordinates": [
        -74.873546,
        10.975448
      ]
    },
    "properties": {}
  },
  {
    "type": "Feature",
    "geometry": {
      "type": "Point",
      "coordinates": [
        -66.874166666667,
        -0.11222222222222
      ]
    },
    "properties": {}
  },
  {
    "type": "Feature",
    "geometry": {
      "type": "Point",
      "coordinates": [
        -67.08388889,
        -0.11888889
      ]
    },
    "properties": {}
  },
  {
    "type": "Feature",
    "geometry": {
      "type": "Point",
      "coordinates": [
        -66.94174,
        9.333095
      ]
    },
    "properties": {}
  },
  {
    "type": "Feature",
    "geometry": {
      "type": "Point",
      "coordinates": [
        -63.33,
        6.83
      ]
    },
    "properties": {}
  },
  {
    "type": "Feature",
    "geometry": {
      "type": "Point",
      "coordinates": [
        -66.925553,
        -0.117683
      ]
    },
    "properties": {}
  },
  {
    "type": "Feature",
    "geometry": {
      "type": "Point",
      "coordinates": [
        -61.88,
        8.03
      ]
    },
    "properties": {}
  },
  {
    "type": "Feature",
    "geometry": {
      "type": "Point",
      "coordinates": [
        -69.925833333333,
        -4.4052777777778
      ]
    },
    "properties": {}
  },
  {
    "type": "Feature",
    "geometry": {
      "type": "Point",
      "coordinates": [
        -67.23,
        -0.056111111111111
      ]
    },
    "properties": {}
  },
  {
    "type": "Feature",
    "geometry": {
      "type": "Point",
      "coordinates": [
        -69.079859,
        -3.961824
      ]
    },
    "properties": {}
  },
  {
    "type": "Feature",
    "geometry": {
      "type": "Point",
      "coordinates": [
        -67.866269,
        5.344189
      ]
    },
    "properties": {}
  },
  {
    "type": "Feature",
    "geometry": {
      "type": "Point",
      "coordinates": [
        -67.115075,
        -0.148294
      ]
    },
    "properties": {}
  },
  {
    "type": "Feature",
    "geometry": {
      "type": "Point",
      "coordinates": [
        -66.461993,
        0.183778
      ]
    },
    "properties": {}
  }
]