[
  {
    "type": "Feature",
    "geometry": {
      "type": "Point",
      "coordinates": [
        -43.3908,
        -18.0042
      ]
    },
    "properties": {}
  },
  {
    "type": "Feature",
    "geometry": {
      "type": "Point",
      "coordinates": [
        -44.18,
        -17.8733
      ]
    },
    "properties": {}
  },
  {
    "type": "Feature",
    "geometry": {
      "type": "Point",
      "coordinates": [
        -43.65298,
        -18.05609
      ]
    },
    "properties": {}
  },
  {
    "type": "Feature",
    "geometry": {
      "type": "Point",
      "coordinates": [
        -47.51,
        -14.1325
      ]
    },
    "properties": {}
  },
  {
    "type": "Feature",
    "geometry": {
      "type": "Point",
      "coordinates": [
        -43.37864,
        -18.13039
      ]
    },
    "properties": {}
  },
  {
    "type": "Feature",
    "geometry": {
      "type": "Point",
      "coordinates": [
        -43.76056,
        -18.28861
      ]
    },
    "properties": {}
  },
  {
    "type": "Feature",
    "geometry": {
      "type": "Point",
      "coordinates": [
        -43.76694,
        -19.00583
      ]
    },
    "properties": {}
  },
  {
    "type": "Feature",
    "geometry": {
      "type": "Point",
      "coordinates": [
        -48.90028,
        -15.79139
      ]
    },
    "properties": {}
  },
  {
    "type": "Feature",
    "geometry": {
      "type": "Point",
      "coordinates": [
        -42.8897,
        -16.5594
      ]
    },
    "properties": {}
  },
  {
    "type": "Feature",
    "geometry": {
      "type": "Point",
      "coordinates": [
        -42.8897,
        -16.5594
      ]
    },
    "properties": {}
  },
  {
    "type": "Feature",
    "geometry": {
      "type": "Point",
      "coordinates": [
        -43.34989,
        -18.14242
      ]
    },
    "properties": {}
  },
  {
    "type": "Feature",
    "geometry": {
      "type": "Point",
      "coordinates": [
        -43.34769,
        -18.12389
      ]
    },
    "properties": {}
  },
  {
    "type": "Feature",
    "geometry": {
      "type": "Point",
      "coordinates": [
        -43.34097,
        -18.09036
      ]
    },
    "properties": {}
  },
  {
    "type": "Feature",
    "geometry": {
      "type": "Point",
      "coordinates": [
        -43.31719,
        -18.15706
      ]
    },
    "properties": {}
  },
  {
    "type": "Feature",
    "geometry": {
      "type": "Point",
      "coordinates": [
        -48.69778,
        -14.53944
      ]
    },
    "properties": {}
  },
  {
    "type": "Feature",
    "geometry": {
      "type": "Point",
      "coordinates": [
        -47.51,
        -14.1325
      ]
    },
    "properties": {}
  },
  {
    "type": "Feature",
    "geometry": {
      "type": "Point",
      "coordinates": [
        -47.51,
        -14.1325
      ]
    },
    "properties": {}
  },
  {
    "type": "Feature",
    "geometry": {
      "type": "Point",
      "coordinates": [
        -47.63611,
        -14.15194
      ]
    },
    "properties": {}
  },
  {
    "type": "Feature",
    "geometry": {
      "type": "Point",
      "coordinates": [
        -47.3344,
        -15.5372
      ]
    },
    "properties": {}
  },
  {
    "type": "Feature",
    "geometry": {
      "type": "Point",
      "coordinates": [
        -47.53512,
        -14.18297
      ]
    },
    "properties": {}
  },
  {
    "type": "Feature",
    "geometry": {
      "type": "Point",
      "coordinates": [
        -46.3658,
        -20.2453
      ]
    },
    "properties": {}
  },
  {
    "type": "Feature",
    "geometry": {
      "type": "Point",
      "coordinates": [
        -46.3658,
        -20.2453
      ]
    },
    "properties": {}
  },
  {
    "type": "Feature",
    "geometry": {
      "type": "Point",
      "coordinates": [
        -42.875,
        -16.35944
      ]
    },
    "properties": {}
  },
  {
    "type": "Feature",
    "geometry": {
      "type": "Point",
      "coordinates": [
        -42.8943,
        -16.5648
      ]
    },
    "properties": {}
  },
  {
    "type": "Feature",
    "geometry": {
      "type": "Point",
      "coordinates": [
        -43.3908,
        -18.0042
      ]
    },
    "properties": {}
  },
  {
    "type": "Feature",
    "geometry": {
      "type": "Point",
      "coordinates": [
        -43.65298,
        -18.05609
      ]
    },
    "properties": {}
  },
  {
    "type": "Feature",
    "geometry": {
      "type": "Point",
      "coordinates": [
        -43.31719,
        -18.15706
      ]
    },
    "properties": {}
  },
  {
    "type": "Feature",
    "geometry": {
      "type": "Point",
      "coordinates": [
        -47.6136,
        -16.7686
      ]
    },
    "properties": {}
  },
  {
    "type": "Feature",
    "geometry": {
      "type": "Point",
      "coordinates": [
        -47.48806,
        -13.97194
      ]
    },
    "properties": {}
  },
  {
    "type": "Feature",
    "geometry": {
      "type": "Point",
      "coordinates": [
        -43.61833,
        -18.21028
      ]
    },
    "properties": {}
  },
  {
    "type": "Feature",
    "geometry": {
      "type": "Point",
      "coordinates": [
        -42.96667,
        -16.6
      ]
    },
    "properties": {}
  },
  {
    "type": "Feature",
    "geometry": {
      "type": "Point",
      "coordinates": [
        -48.21667,
        -14.15
      ]
    },
    "properties": {}
  },
  {
    "type": "Feature",
    "geometry": {
      "type": "Point",
      "coordinates": [
        -43.6003,
        -18.2494
      ]
    },
    "properties": {}
  },
  {
    "type": "Feature",
    "geometry": {
      "type": "Point",
      "coordinates": [
        -43.6003,
        -18.2494
      ]
    },
    "properties": {}
  },
  {
    "type": "Feature",
    "geometry": {
      "type": "Point",
      "coordinates": [
        -46.3658,
        -20.2453
      ]
    },
    "properties": {}
  },
  {
    "type": "Feature",
    "geometry": {
      "type": "Point",
      "coordinates": [
        -43.6003,
        -18.2494
      ]
    },
    "properties": {}
  },
  {
    "type": "Feature",
    "geometry": {
      "type": "Point",
      "coordinates": [
        -43.7408,
        -18.4544
      ]
    },
    "properties": {}
  },
  {
    "type": "Feature",
    "geometry": {
      "type": "Point",
      "coordinates": [
        -50.19,
        -16.07722
      ]
    },
    "properties": {}
  },
  {
    "type": "Feature",
    "geometry": {
      "type": "Point",
      "coordinates": [
        -50.19,
        -16.07722
      ]
    },
    "properties": {}
  },
  {
    "type": "Feature",
    "geometry": {
      "type": "Point",
      "coordinates": [
        -42.994,
        -16.4639
      ]
    },
    "properties": {}
  },
  {
    "type": "Feature",
    "geometry": {
      "type": "Point",
      "coordinates": [
        -47,
        -14
      ]
    },
    "properties": {}
  },
  {
    "type": "Feature",
    "geometry": {
      "type": "Point",
      "coordinates": [
        -43.62083,
        -17.78778
      ]
    },
    "properties": {}
  },
  {
    "type": "Feature",
    "geometry": {
      "type": "Point",
      "coordinates": [
        -50.215,
        -16.1267
      ]
    },
    "properties": {}
  },
  {
    "type": "Feature",
    "geometry": {
      "type": "Point",
      "coordinates": [
        -47.80667,
        -13.68222
      ]
    },
    "properties": {}
  },
  {
    "type": "Feature",
    "geometry": {
      "type": "Point",
      "coordinates": [
        -43.3908,
        -18.0042
      ]
    },
    "properties": {}
  },
  {
    "type": "Feature",
    "geometry": {
      "type": "Point",
      "coordinates": [
        -42.8897,
        -16.5594
      ]
    },
    "properties": {}
  },
  {
    "type": "Feature",
    "geometry": {
      "type": "Point",
      "coordinates": [
        -43.6003,
        -18.2494
      ]
    },
    "properties": {}
  },
  {
    "type": "Feature",
    "geometry": {
      "type": "Point",
      "coordinates": [
        -42.89389,
        -16.55722
      ]
    },
    "properties": {}
  },
  {
    "type": "Feature",
    "geometry": {
      "type": "Point",
      "coordinates": [
        -43.61472,
        -18.14806
      ]
    },
    "properties": {}
  },
  {
    "type": "Feature",
    "geometry": {
      "type": "Point",
      "coordinates": [
        -43.0108,
        -16.8722
      ]
    },
    "properties": {}
  },
  {
    "type": "Feature",
    "geometry": {
      "type": "Point",
      "coordinates": [
        -42.8897,
        -16.5594
      ]
    },
    "properties": {}
  },
  {
    "type": "Feature",
    "geometry": {
      "type": "Point",
      "coordinates": [
        -47.4583,
        -13.7975
      ]
    },
    "properties": {}
  },
  {
    "type": "Feature",
    "geometry": {
      "type": "Point",
      "coordinates": [
        -43.76056,
        -18.28861
      ]
    },
    "properties": {}
  },
  {
    "type": "Feature",
    "geometry": {
      "type": "Point",
      "coordinates": [
        -48.4597,
        -14.4739
      ]
    },
    "properties": {}
  },
  {
    "type": "Feature",
    "geometry": {
      "type": "Point",
      "coordinates": [
        -48.91806,
        -15.8125
      ]
    },
    "properties": {}
  },
  {
    "type": "Feature",
    "geometry": {
      "type": "Point",
      "coordinates": [
        -42.994,
        -16.4639
      ]
    },
    "properties": {}
  },
  {
    "type": "Feature",
    "geometry": {
      "type": "Point",
      "coordinates": [
        -48.04607,
        -14.07484
      ]
    },
    "properties": {}
  },
  {
    "type": "Feature",
    "geometry": {
      "type": "Point",
      "coordinates": [
        -48.55722,
        -14.48861
      ]
    },
    "properties": {}
  },
  {
    "type": "Feature",
    "geometry": {
      "type": "Point",
      "coordinates": [
        -47.525,
        -13.59972
      ]
    },
    "properties": {}
  },
  {
    "type": "Feature",
    "geometry": {
      "type": "Point",
      "coordinates": [
        -43.90112,
        -18.91577
      ]
    },
    "properties": {}
  },
  {
    "type": "Feature",
    "geometry": {
      "type": "Point",
      "coordinates": [
        -47.33444,
        -15.53722
      ]
    },
    "properties": {}
  },
  {
    "type": "Feature",
    "geometry": {
      "type": "Point",
      "coordinates": [
        -50.215,
        -16.1267
      ]
    },
    "properties": {}
  },
  {
    "type": "Feature",
    "geometry": {
      "type": "Point",
      "coordinates": [
        -42.86667,
        -16.53333
      ]
    },
    "properties": {}
  },
  {
    "type": "Feature",
    "geometry": {
      "type": "Point",
      "coordinates": [
        -47.48333,
        -14.03333
      ]
    },
    "properties": {}
  },
  {
    "type": "Feature",
    "geometry": {
      "type": "Point",
      "coordinates": [
        -47.53512,
        -14.18297
      ]
    },
    "properties": {}
  },
  {
    "type": "Feature",
    "geometry": {
      "type": "Point",
      "coordinates": [
        -43.61667,
        -18.18333
      ]
    },
    "properties": {}
  },
  {
    "type": "Feature",
    "geometry": {
      "type": "Point",
      "coordinates": [
        -47.4583,
        -13.7975
      ]
    },
    "properties": {}
  },
  {
    "type": "Feature",
    "geometry": {
      "type": "Point",
      "coordinates": [
        -43.6003,
        -18.2494
      ]
    },
    "properties": {}
  },
  {
    "type": "Feature",
    "geometry": {
      "type": "Point",
      "coordinates": [
        -47.4583,
        -13.7975
      ]
    },
    "properties": {}
  },
  {
    "type": "Feature",
    "geometry": {
      "type": "Point",
      "coordinates": [
        -47.51,
        -14.1325
      ]
    },
    "properties": {}
  },
  {
    "type": "Feature",
    "geometry": {
      "type": "Point",
      "coordinates": [
        -43.6003,
        -18.2494
      ]
    },
    "properties": {}
  },
  {
    "type": "Feature",
    "geometry": {
      "type": "Point",
      "coordinates": [
        -43.55,
        -18.17
      ]
    },
    "properties": {}
  },
  {
    "type": "Feature",
    "geometry": {
      "type": "Point",
      "coordinates": [
        -43.6003,
        -18.2494
      ]
    },
    "properties": {}
  },
  {
    "type": "Feature",
    "geometry": {
      "type": "Point",
      "coordinates": [
        -42.92667,
        -16.72333
      ]
    },
    "properties": {}
  },
  {
    "type": "Feature",
    "geometry": {
      "type": "Point",
      "coordinates": [
        -43.43284,
        -18.09029
      ]
    },
    "properties": {}
  },
  {
    "type": "Feature",
    "geometry": {
      "type": "Point",
      "coordinates": [
        -43.33856,
        -18.10986
      ]
    },
    "properties": {}
  },
  {
    "type": "Feature",
    "geometry": {
      "type": "Point",
      "coordinates": [
        -47.4583,
        -13.7975
      ]
    },
    "properties": {}
  },
  {
    "type": "Feature",
    "geometry": {
      "type": "Point",
      "coordinates": [
        -42.73139,
        -15.655
      ]
    },
    "properties": {}
  },
  {
    "type": "Feature",
    "geometry": {
      "type": "Point",
      "coordinates": [
        -44.26215,
        -17.69803
      ]
    },
    "properties": {}
  },
  {
    "type": "Feature",
    "geometry": {
      "type": "Point",
      "coordinates": [
        -43.6003,
        -18.2494
      ]
    },
    "properties": {}
  },
  {
    "type": "Feature",
    "geometry": {
      "type": "Point",
      "coordinates": [
        -48.4597,
        -14.4739
      ]
    },
    "properties": {}
  },
  {
    "type": "Feature",
    "geometry": {
      "type": "Point",
      "coordinates": [
        -43.34769,
        -18.12389
      ]
    },
    "properties": {}
  },
  {
    "type": "Feature",
    "geometry": {
      "type": "Point",
      "coordinates": [
        -47.51,
        -14.1325
      ]
    },
    "properties": {}
  },
  {
    "type": "Feature",
    "geometry": {
      "type": "Point",
      "coordinates": [
        -43.04861,
        -16.83861
      ]
    },
    "properties": {}
  },
  {
    "type": "Feature",
    "geometry": {
      "type": "Point",
      "coordinates": [
        -43.6003,
        -18.2494
      ]
    },
    "properties": {}
  },
  {
    "type": "Feature",
    "geometry": {
      "type": "Point",
      "coordinates": [
        -47.43333,
        -14.03333
      ]
    },
    "properties": {}
  },
  {
    "type": "Feature",
    "geometry": {
      "type": "Point",
      "coordinates": [
        -43.3908,
        -18.0042
      ]
    },
    "properties": {}
  },
  {
    "type": "Feature",
    "geometry": {
      "type": "Point",
      "coordinates": [
        -43.6003,
        -18.2494
      ]
    },
    "properties": {}
  },
  {
    "type": "Feature",
    "geometry": {
      "type": "Point",
      "coordinates": [
        -43.2075,
        -22.9028
      ]
    },
    "properties": {}
  },
  {
    "type": "Feature",
    "geometry": {
      "type": "Point",
      "coordinates": [
        -48.0783,
        -14.1514
      ]
    },
    "properties": {}
  },
  {
    "type": "Feature",
    "geometry": {
      "type": "Point",
      "coordinates": [
        -47.63917,
        -14.06
      ]
    },
    "properties": {}
  },
  {
    "type": "Feature",
    "geometry": {
      "type": "Point",
      "coordinates": [
        -43.75583,
        -19.00333
      ]
    },
    "properties": {}
  },
  {
    "type": "Feature",
    "geometry": {
      "type": "Point",
      "coordinates": [
        -44.2342,
        -17.315
      ]
    },
    "properties": {}
  },
  {
    "type": "Feature",
    "geometry": {
      "type": "Point",
      "coordinates": [
        -47.91972,
        -14.21528
      ]
    },
    "properties": {}
  },
  {
    "type": "Feature",
    "geometry": {
      "type": "Point",
      "coordinates": [
        -43.82075,
        -17.90964
      ]
    },
    "properties": {}
  },
  {
    "type": "Feature",
    "geometry": {
      "type": "Point",
      "coordinates": [
        -48.55722,
        -14.48861
      ]
    },
    "properties": {}
  },
  {
    "type": "Feature",
    "geometry": {
      "type": "Point",
      "coordinates": [
        -43.6003,
        -18.2494
      ]
    },
    "properties": {}
  },
  {
    "type": "Feature",
    "geometry": {
      "type": "Point",
      "coordinates": [
        -48.45,
        -14.49611
      ]
    },
    "properties": {}
  },
  {
    "type": "Feature",
    "geometry": {
      "type": "Point",
      "coordinates": [
        -47.4583,
        -13.7975
      ]
    },
    "properties": {}
  },
  {
    "type": "Feature",
    "geometry": {
      "type": "Point",
      "coordinates": [
        -47.51667,
        -14.11667
      ]
    },
    "properties": {}
  },
  {
    "type": "Feature",
    "geometry": {
      "type": "Point",
      "coordinates": [
        -43.55,
        -18.26667
      ]
    },
    "properties": {}
  },
  {
    "type": "Feature",
    "geometry": {
      "type": "Point",
      "coordinates": [
        -42.89528,
        -16.55556
      ]
    },
    "properties": {}
  },
  {
    "type": "Feature",
    "geometry": {
      "type": "Point",
      "coordinates": [
        -47.69611,
        -13.94389
      ]
    },
    "properties": {}
  },
  {
    "type": "Feature",
    "geometry": {
      "type": "Point",
      "coordinates": [
        -43.3908,
        -18.0042
      ]
    },
    "properties": {}
  },
  {
    "type": "Feature",
    "geometry": {
      "type": "Point",
      "coordinates": [
        -42.8897,
        -16.5594
      ]
    },
    "properties": {}
  },
  {
    "type": "Feature",
    "geometry": {
      "type": "Point",
      "coordinates": [
        -48.12222,
        -13.89722
      ]
    },
    "properties": {}
  },
  {
    "type": "Feature",
    "geometry": {
      "type": "Point",
      "coordinates": [
        -43.65298,
        -18.05609
      ]
    },
    "properties": {}
  },
  {
    "type": "Feature",
    "geometry": {
      "type": "Point",
      "coordinates": [
        -42.8897,
        -16.5594
      ]
    },
    "properties": {}
  },
  {
    "type": "Feature",
    "geometry": {
      "type": "Point",
      "coordinates": [
        -44.1722,
        -17.7575
      ]
    },
    "properties": {}
  },
  {
    "type": "Feature",
    "geometry": {
      "type": "Point",
      "coordinates": [
        -43.6003,
        -18.2494
      ]
    },
    "properties": {}
  },
  {
    "type": "Feature",
    "geometry": {
      "type": "Point",
      "coordinates": [
        -43.6003,
        -18.2494
      ]
    },
    "properties": {}
  },
  {
    "type": "Feature",
    "geometry": {
      "type": "Point",
      "coordinates": [
        -47.50917,
        -14.0725
      ]
    },
    "properties": {}
  },
  {
    "type": "Feature",
    "geometry": {
      "type": "Point",
      "coordinates": [
        -47.61667,
        -14.15
      ]
    },
    "properties": {}
  },
  {
    "type": "Feature",
    "geometry": {
      "type": "Point",
      "coordinates": [
        -47.45778,
        -13.82278
      ]
    },
    "properties": {}
  },
  {
    "type": "Feature",
    "geometry": {
      "type": "Point",
      "coordinates": [
        -47.59306,
        -14.16333
      ]
    },
    "properties": {}
  },
  {
    "type": "Feature",
    "geometry": {
      "type": "Point",
      "coordinates": [
        -43.6003,
        -18.2494
      ]
    },
    "properties": {}
  },
  {
    "type": "Feature",
    "geometry": {
      "type": "Point",
      "coordinates": [
        -43.77139,
        -18.96333
      ]
    },
    "properties": {}
  },
  {
    "type": "Feature",
    "geometry": {
      "type": "Point",
      "coordinates": [
        -43.37864,
        -18.13039
      ]
    },
    "properties": {}
  },
  {
    "type": "Feature",
    "geometry": {
      "type": "Point",
      "coordinates": [
        -43.34639,
        -17.03833
      ]
    },
    "properties": {}
  },
  {
    "type": "Feature",
    "geometry": {
      "type": "Point",
      "coordinates": [
        -43.3908,
        -18.0042
      ]
    },
    "properties": {}
  },
  {
    "type": "Feature",
    "geometry": {
      "type": "Point",
      "coordinates": [
        -42.95,
        -16.58333
      ]
    },
    "properties": {}
  },
  {
    "type": "Feature",
    "geometry": {
      "type": "Point",
      "coordinates": [
        -43.59444,
        -18.24194
      ]
    },
    "properties": {}
  },
  {
    "type": "Feature",
    "geometry": {
      "type": "Point",
      "coordinates": [
        -43.54167,
        -18.17639
      ]
    },
    "properties": {}
  },
  {
    "type": "Feature",
    "geometry": {
      "type": "Point",
      "coordinates": [
        -47.00021,
        -14.00086
      ]
    },
    "properties": {}
  },
  {
    "type": "Feature",
    "geometry": {
      "type": "Point",
      "coordinates": [
        -47,
        -14
      ]
    },
    "properties": {}
  }
]