[
  {
    "type": "Feature",
    "geometry": {
      "type": "Point",
      "coordinates": [
        -60.320833333333,
        -2.5636111111111
      ]
    },
    "properties": {}
  },
  {
    "type": "Feature",
    "geometry": {
      "type": "Point",
      "coordinates": [
        -59.572513,
        -2.656591
      ]
    },
    "properties": {}
  },
  {
    "type": "Feature",
    "geometry": {
      "type": "Point",
      "coordinates": [
        -60.38365,
        -2.985394
      ]
    },
    "properties": {}
  },
  {
    "type": "Feature",
    "geometry": {
      "type": "Point",
      "coordinates": [
        -59.931956,
        -2.940846
      ]
    },
    "properties": {}
  },
  {
    "type": "Feature",
    "geometry": {
      "type": "Point",
      "coordinates": [
        -61.436182,
        -4.890079
      ]
    },
    "properties": {}
  },
  {
    "type": "Feature",
    "geometry": {
      "type": "Point",
      "coordinates": [
        -59.928055555556,
        -2.9605555555556
      ]
    },
    "properties": {}
  },
  {
    "type": "Feature",
    "geometry": {
      "type": "Point",
      "coordinates": [
        -59.925512,
        -3.093994
      ]
    },
    "properties": {}
  },
  {
    "type": "Feature",
    "geometry": {
      "type": "Point",
      "coordinates": [
        -59,
        -2.416667
      ]
    },
    "properties": {}
  },
  {
    "type": "Feature",
    "geometry": {
      "type": "Point",
      "coordinates": [
        -59.931555,
        -2.958287
      ]
    },
    "properties": {}
  },
  {
    "type": "Feature",
    "geometry": {
      "type": "Point",
      "coordinates": [
        -60.869722222222,
        -2.4838888888889
      ]
    },
    "properties": {}
  },
  {
    "type": "Feature",
    "geometry": {
      "type": "Point",
      "coordinates": [
        -60.114474,
        -2.603425
      ]
    },
    "properties": {}
  },
  {
    "type": "Feature",
    "geometry": {
      "type": "Point",
      "coordinates": [
        -60.08,
        -2.32
      ]
    },
    "properties": {}
  },
  {
    "type": "Feature",
    "geometry": {
      "type": "Point",
      "coordinates": [
        -59.92929,
        -2.95728
      ]
    },
    "properties": {}
  },
  {
    "type": "Feature",
    "geometry": {
      "type": "Point",
      "coordinates": [
        -59.8667,
        -2.4
      ]
    },
    "properties": {}
  },
  {
    "type": "Feature",
    "geometry": {
      "type": "Point",
      "coordinates": [
        -59.789207,
        -2.733853
      ]
    },
    "properties": {}
  },
  {
    "type": "Feature",
    "geometry": {
      "type": "Point",
      "coordinates": [
        -59.5,
        -1.5
      ]
    },
    "properties": {}
  },
  {
    "type": "Feature",
    "geometry": {
      "type": "Point",
      "coordinates": [
        -60.320833333333,
        -2.5636111111111
      ]
    },
    "properties": {}
  },
  {
    "type": "Feature",
    "geometry": {
      "type": "Point",
      "coordinates": [
        -59.934008,
        -2.952882
      ]
    },
    "properties": {}
  },
  {
    "type": "Feature",
    "geometry": {
      "type": "Point",
      "coordinates": [
        -62.17350551,
        -2.430289463
      ]
    },
    "properties": {}
  },
  {
    "type": "Feature",
    "geometry": {
      "type": "Point",
      "coordinates": [
        -59.985523,
        -3.097896
      ]
    },
    "properties": {}
  },
  {
    "type": "Feature",
    "geometry": {
      "type": "Point",
      "coordinates": [
        -59.931976,
        -3.083152
      ]
    },
    "properties": {}
  },
  {
    "type": "Feature",
    "geometry": {
      "type": "Point",
      "coordinates": [
        -58.06092284,
        -4.984780943
      ]
    },
    "properties": {}
  },
  {
    "type": "Feature",
    "geometry": {
      "type": "Point",
      "coordinates": [
        -60.508888888889,
        -2.8275
      ]
    },
    "properties": {}
  },
  {
    "type": "Feature",
    "geometry": {
      "type": "Point",
      "coordinates": [
        -59.910452,
        -2.77081
      ]
    },
    "properties": {}
  },
  {
    "type": "Feature",
    "geometry": {
      "type": "Point",
      "coordinates": [
        -59.934745,
        -2.959795
      ]
    },
    "properties": {}
  },
  {
    "type": "Feature",
    "geometry": {
      "type": "Point",
      "coordinates": [
        -60,
        -2.316667
      ]
    },
    "properties": {}
  },
  {
    "type": "Feature",
    "geometry": {
      "type": "Point",
      "coordinates": [
        -60.088042,
        -2.87455
      ]
    },
    "properties": {}
  },
  {
    "type": "Feature",
    "geometry": {
      "type": "Point",
      "coordinates": [
        -59.929631,
        -2.95992
      ]
    },
    "properties": {}
  },
  {
    "type": "Feature",
    "geometry": {
      "type": "Point",
      "coordinates": [
        -59.923722,
        -2.962435
      ]
    },
    "properties": {}
  },
  {
    "type": "Feature",
    "geometry": {
      "type": "Point",
      "coordinates": [
        -59.926971,
        -2.954756
      ]
    },
    "properties": {}
  },
  {
    "type": "Feature",
    "geometry": {
      "type": "Point",
      "coordinates": [
        -59.87,
        -2.4
      ]
    },
    "properties": {}
  },
  {
    "type": "Feature",
    "geometry": {
      "type": "Point",
      "coordinates": [
        -59.924159,
        -2.955868
      ]
    },
    "properties": {}
  },
  {
    "type": "Feature",
    "geometry": {
      "type": "Point",
      "coordinates": [
        -59.930715,
        -2.957496
      ]
    },
    "properties": {}
  },
  {
    "type": "Feature",
    "geometry": {
      "type": "Point",
      "coordinates": [
        -59.25164,
        -1.805254
      ]
    },
    "properties": {}
  },
  {
    "type": "Feature",
    "geometry": {
      "type": "Point",
      "coordinates": [
        -60.067579,
        -3.000133
      ]
    },
    "properties": {}
  },
  {
    "type": "Feature",
    "geometry": {
      "type": "Point",
      "coordinates": [
        -58.06092284,
        -4.984780943
      ]
    },
    "properties": {}
  },
  {
    "type": "Feature",
    "geometry": {
      "type": "Point",
      "coordinates": [
        -60.08,
        -2.32
      ]
    },
    "properties": {}
  },
  {
    "type": "Feature",
    "geometry": {
      "type": "Point",
      "coordinates": [
        -59.792512,
        -2.712883
      ]
    },
    "properties": {}
  },
  {
    "type": "Feature",
    "geometry": {
      "type": "Point",
      "coordinates": [
        -59.930247,
        -2.954375
      ]
    },
    "properties": {}
  },
  {
    "type": "Feature",
    "geometry": {
      "type": "Point",
      "coordinates": [
        -59.926262,
        -2.958416
      ]
    },
    "properties": {}
  },
  {
    "type": "Feature",
    "geometry": {
      "type": "Point",
      "coordinates": [
        -59.928516,
        -3.089206
      ]
    },
    "properties": {}
  },
  {
    "type": "Feature",
    "geometry": {
      "type": "Point",
      "coordinates": [
        -59.929247,
        -2.966739
      ]
    },
    "properties": {}
  },
  {
    "type": "Feature",
    "geometry": {
      "type": "Point",
      "coordinates": [
        -59.933535,
        -2.95524
      ]
    },
    "properties": {}
  },
  {
    "type": "Feature",
    "geometry": {
      "type": "Point",
      "coordinates": [
        -59.930642,
        -2.957343
      ]
    },
    "properties": {}
  },
  {
    "type": "Feature",
    "geometry": {
      "type": "Point",
      "coordinates": [
        -59.930645,
        -2.961768
      ]
    },
    "properties": {}
  },
  {
    "type": "Feature",
    "geometry": {
      "type": "Point",
      "coordinates": [
        -59.940904,
        -2.964358
      ]
    },
    "properties": {}
  },
  {
    "type": "Feature",
    "geometry": {
      "type": "Point",
      "coordinates": [
        -60.39203249,
        -2.536873616
      ]
    },
    "properties": {}
  },
  {
    "type": "Feature",
    "geometry": {
      "type": "Point",
      "coordinates": [
        -59.928055555556,
        -2.9605555555556
      ]
    },
    "properties": {}
  },
  {
    "type": "Feature",
    "geometry": {
      "type": "Point",
      "coordinates": [
        -59.9317,
        -2.957262
      ]
    },
    "properties": {}
  },
  {
    "type": "Feature",
    "geometry": {
      "type": "Point",
      "coordinates": [
        -60.025001525879,
        -2.0344400405884
      ]
    },
    "properties": {}
  },
  {
    "type": "Feature",
    "geometry": {
      "type": "Point",
      "coordinates": [
        -59.945186,
        -3.138984
      ]
    },
    "properties": {}
  },
  {
    "type": "Feature",
    "geometry": {
      "type": "Point",
      "coordinates": [
        -59.268383,
        -1.811187
      ]
    },
    "properties": {}
  },
  {
    "type": "Feature",
    "geometry": {
      "type": "Point",
      "coordinates": [
        -59.935594,
        -2.961899
      ]
    },
    "properties": {}
  },
  {
    "type": "Feature",
    "geometry": {
      "type": "Point",
      "coordinates": [
        -59.932387,
        -2.961508
      ]
    },
    "properties": {}
  },
  {
    "type": "Feature",
    "geometry": {
      "type": "Point",
      "coordinates": [
        -59.705472,
        -2.736611
      ]
    },
    "properties": {}
  },
  {
    "type": "Feature",
    "geometry": {
      "type": "Point",
      "coordinates": [
        -59.924277,
        -2.958995
      ]
    },
    "properties": {}
  },
  {
    "type": "Feature",
    "geometry": {
      "type": "Point",
      "coordinates": [
        -61.25,
        -1.75
      ]
    },
    "properties": {}
  },
  {
    "type": "Feature",
    "geometry": {
      "type": "Point",
      "coordinates": [
        -59.933892,
        -2.958806
      ]
    },
    "properties": {}
  }
]