[{"class":"Formação florestal","annualRate":0.0456,"pValue":3.5282e-17,"rSquared":0.8717},{"class":"Formação savânica","annualRate":0.9579,"pValue":0.0000054988,"rSquared":0.4502},{"class":"Formação campestre","annualRate":-0.0037,"pValue":9.5333e-10,"rSquared":0.6614},{"class":"Pastagem","annualRate":-0.8115,"pValue":0.0001,"rSquared":0.3789},{"class":"Mosaico de usos","annualRate":-0.1213,"pValue":0.0065,"rSquared":0.193},{"class":"Áreas não vegetadas","annualRate":0.005,"pValue":0.0288,"rSquared":0.1293},{"class":"Outras áreas não vegetadas","annualRate":0.0112,"pValue":0.0014,"rSquared":0.2557},{"class":"Rio, lago e oceano","annualRate":-0.0858,"pValue":5.7948e-12,"rSquared":0.7463},{"class":"Café","annualRate":0.0027,"pValue":0.0165,"rSquared":0.1535},{"class":"Natural","annualRate":0.9301,"pValue":0.0000092132,"rSquared":0.4343},{"class":"Uso alternativo","annualRate":-0.9301,"pValue":0.0000092132,"rSquared":0.4343}]