[{"class":"Formação florestal","annualRate":0.186,"pValue":5.1471e-10,"rSquared":0.673},{"class":"Formação savânica","annualRate":0.0038,"pValue":7.5205e-11,"rSquared":0.7067},{"class":"Silvicultura","annualRate":0.0006,"pValue":0.0921,"rSquared":0.0789},{"class":"Formação campestre","annualRate":1.7822,"pValue":2.0637e-25,"rSquared":0.9565},{"class":"Pastagem","annualRate":-1.4999,"pValue":1.6375e-27,"rSquared":0.967},{"class":"Lavoura temporária","annualRate":-0.0579,"pValue":0,"rSquared":0.4108},{"class":"Mosaico de usos","annualRate":-0.2735,"pValue":0,"rSquared":0.4086},{"class":"Áreas não vegetadas","annualRate":0.0217,"pValue":0.0921,"rSquared":0.0789},{"class":"Lavoura perene","annualRate":-0.163,"pValue":3.3418e-13,"rSquared":0.7842},{"class":"Natural","annualRate":1.9937,"pValue":6.3004e-28,"rSquared":0.9687},{"class":"Uso alternativo","annualRate":-1.9937,"pValue":6.3004e-28,"rSquared":0.9687}]