[{"class":"Out","annualRate":-0.0001,"pValue":0.3332,"rSquared":0.0268},{"class":"Formação florestal","annualRate":-0.1923,"pValue":6.1465e-11,"rSquared":0.71},{"class":"Formação savânica","annualRate":0.0048,"pValue":0.0806,"rSquared":0.0847},{"class":"Silvicultura","annualRate":0.1991,"pValue":7.6198e-23,"rSquared":0.939},{"class":"Campo alagado e área pantanosa","annualRate":0.0059,"pValue":0.0000069099,"rSquared":0.4432},{"class":"Formação campestre","annualRate":0.0533,"pValue":3.9835e-12,"rSquared":0.7516},{"class":"Pastagem","annualRate":-0.2475,"pValue":0.0000019671,"rSquared":0.4807},{"class":"Lavoura temporária","annualRate":0.001,"pValue":0.000008196,"rSquared":0.4379},{"class":"Mosaico de usos","annualRate":0.0966,"pValue":0.0024,"rSquared":0.2335},{"class":"Áreas não vegetadas","annualRate":0.0963,"pValue":2.4059e-29,"rSquared":0.974},{"class":"Área urbanizada","annualRate":0.0184,"pValue":9.6152e-23,"rSquared":0.9382},{"class":"Outras áreas não vegetadas","annualRate":-0.0033,"pValue":0.0000033469,"rSquared":0.4651},{"class":"Afloramento rochoso","annualRate":-0.0229,"pValue":0.0000099449,"rSquared":0.4319},{"class":"Mineração","annualRate":0.0034,"pValue":1.1043e-21,"rSquared":0.929},{"class":"Rio, lago e oceano","annualRate":-0.0116,"pValue":1.9276e-15,"rSquared":0.8389},{"class":"Lavoura perene","annualRate":-0.0022,"pValue":1.1952e-11,"rSquared":0.7356},{"class":"Soja","annualRate":0.0032,"pValue":6.8004e-9,"rSquared":0.6218},{"class":"Outras lavouras temporárias","annualRate":0.0017,"pValue":0,"rSquared":0.3864},{"class":"Café","annualRate":-0.0038,"pValue":0.0028,"rSquared":0.228},{"class":"Outras lavouras perenes","annualRate":0.0001,"pValue":0,"rSquared":0.4066},{"class":"Natural","annualRate":-0.0699,"pValue":0,"rSquared":0.3854},{"class":"Uso alternativo","annualRate":0.07,"pValue":0,"rSquared":0.3859}]